audiapi/API.py
audiapi/Services.py
audiapi/Token.py
audiapi/__init__.py
audiapi/model/ClimaRequest.py
audiapi/model/CurrentVehicleDataResponse.py
audiapi/model/HonkFlash.py
audiapi/model/OperationsID.py
audiapi/model/PinAuth.py
audiapi/model/RequestStatus.py
audiapi/model/ServiceID.py
audiapi/model/Vehicle.py
audiapi/model/VehicleDataResponse.py
audiapi/model/__init__.py
audiapi-1.0.1.dist-info/METADATA
audiapi-1.0.1.dist-info/WHEEL
audiapi-1.0.1.dist-info/top_level.txt
audiapi-1.0.1.dist-info/RECORD
