Metadata-Version: 2.1
Name: audiapi
Version: 1.0.1
Summary: Provides access to the Audi Connect API
Home-page: https://github.com/davidgiga1993/AudiAPI
Author: davidgiga1993
Author-email: david@dev-core.org
License: UNKNOWN
Platform: UNKNOWN
Classifier: Development Status :: 4 - Beta
Classifier: Programming Language :: Python :: 3
Classifier: License :: OSI Approved :: MIT License
Classifier: Operating System :: OS Independent
Classifier: Topic :: Software Development :: Libraries
